iscurse/__init__.py
iscurse/analyzer.py
iscurse-0.0.8.dist-info/LICENSE
iscurse-0.0.8.dist-info/METADATA
iscurse-0.0.8.dist-info/WHEEL
iscurse-0.0.8.dist-info/top_level.txt
iscurse-0.0.8.dist-info/RECORD
