Metadata-Version: 2.1
Name: iscurse
Version: 0.0.8
Summary: short sentiment analysis
Author: Daniel Yudi
Author-email: <danielyudicarvalho@gmail.com>
License: UNKNOWN
Keywords: curse,sentiment,analysis
Platform: UNKNOWN
Classifier: Development Status :: 1 - Planning
Classifier: Intended Audience :: Developers
Classifier: Programming Language :: Python :: 3
Classifier: Operating System :: Unix
Classifier: Operating System :: MacOS :: MacOS X
Classifier: Operating System :: Microsoft :: Windows
License-File: LICENSE
